{
  "archiveName": "lvmp011",
  "speciesId": 11,
  "recordCount": 100,
  "records": [
    {
      "level": 1,
      "expRequired": 0,
      "gainHP": 0,
      "gainAtk": 0,
      "gainSpAtk": 0,
      "gainDef": 0,
      "gainSpDef": 0,
      "fillA": 0
    },
    {
      "level": 2,
      "expRequired": 400,
      "gainHP": 1,
      "gainAtk": 0,
      "gainSpAtk": 0,
      "gainDef": 1,
      "gainSpDef": 0,
      "fillA": 0
    },
    {
      "level": 3,
      "expRequired": 1000,
      "gainHP": 0,
      "gainAtk": 1,
      "gainSpAtk": 0,
      "gainDef": 0,
      "gainSpDef": 1,
      "fillA": 0
    },
    {
      "level": 4,
      "expRequired": 1800,
      "gainHP": 1,
      "gainAtk": 0,
      "gainSpAtk": 1,
      "gainDef": 0,
      "gainSpDef": 0,
      "fillA": 0
    },
    {
      "level": 5,
      "expRequired": 3000,
      "gainHP": 0,
      "gainAtk": 1,
      "gainSpAtk": 0,
      "gainDef": 1,
      "gainSpDef": 0,
      "fillA": 0
    },
    {
      "level": 6,
      "expRequired": 4500,
      "gainHP": 1,
      "gainAtk": 0,
      "gainSpAtk": 0,
      "gainDef": 0,
      "gainSpDef": 1,
      "fillA": 0
    },
    {
      "level": 7,
      "expRequired": 6000,
      "gainHP": 0,
      "gainAtk": 1,
      "gainSpAtk": 1,
      "gainDef": 0,
      "gainSpDef": 0,
      "fillA": 0
    },
    {
      "level": 8,
      "expRequired": 7500,
      "gainHP": 1,
      "gainAtk": 0,
      "gainSpAtk": 0,
      "gainDef": 1,
      "gainSpDef": 0,
      "fillA": 0
    },
    {
      "level": 9,
      "expRequired": 9000,
      "gainHP": 0,
      "gainAtk": 1,
      "gainSpAtk": 0,
      "gainDef": 0,
      "gainSpDef": 1,
      "fillA": 0
    },
    {
      "level": 10,
      "expRequired": 10500,
      "gainHP": 1,
      "gainAtk": 0,
      "gainSpAtk": 1,
      "gainDef": 0,
      "gainSpDef": 0,
      "fillA": 0
    },
    {
      "level": 11,
      "expRequired": 12000,
      "gainHP": 0,
      "gainAtk": 1,
      "gainSpAtk": 0,
      "gainDef": 1,
      "gainSpDef": 0,
      "fillA": 0
    },
    {
      "level": 12,
      "expRequired": 13500,
      "gainHP": 1,
      "gainAtk": 0,
      "gainSpAtk": 0,
      "gainDef": 0,
      "gainSpDef": 1,
      "fillA": 0
    },
    {
      "level": 13,
      "expRequired": 15000,
      "gainHP": 0,
      "gainAtk": 1,
      "gainSpAtk": 1,
      "gainDef": 0,
      "gainSpDef": 0,
      "fillA": 0
    },
    {
      "level": 14,
      "expRequired": 16500,
      "gainHP": 1,
      "gainAtk": 0,
      "gainSpAtk": 0,
      "gainDef": 1,
      "gainSpDef": 0,
      "fillA": 0
    },
    {
      "level": 15,
      "expRequired": 18500,
      "gainHP": 0,
      "gainAtk": 1,
      "gainSpAtk": 0,
      "gainDef": 0,
      "gainSpDef": 1,
      "fillA": 0
    },
    {
      "level": 16,
      "expRequired": 20500,
      "gainHP": 1,
      "gainAtk": 0,
      "gainSpAtk": 1,
      "gainDef": 0,
      "gainSpDef": 0,
      "fillA": 0
    },
    {
      "level": 17,
      "expRequired": 22500,
      "gainHP": 0,
      "gainAtk": 1,
      "gainSpAtk": 0,
      "gainDef": 1,
      "gainSpDef": 0,
      "fillA": 0
    },
    {
      "level": 18,
      "expRequired": 25300,
      "gainHP": 1,
      "gainAtk": 0,
      "gainSpAtk": 0,
      "gainDef": 0,
      "gainSpDef": 1,
      "fillA": 0
    },
    {
      "level": 19,
      "expRequired": 30300,
      "gainHP": 0,
      "gainAtk": 1,
      "gainSpAtk": 1,
      "gainDef": 0,
      "gainSpDef": 0,
      "fillA": 0
    },
    {
      "level": 20,
      "expRequired": 35300,
      "gainHP": 1,
      "gainAtk": 0,
      "gainSpAtk": 0,
      "gainDef": 1,
      "gainSpDef": 0,
      "fillA": 0
    },
    {
      "level": 21,
      "expRequired": 43000,
      "gainHP": 0,
      "gainAtk": 1,
      "gainSpAtk": 0,
      "gainDef": 0,
      "gainSpDef": 1,
      "fillA": 0
    },
    {
      "level": 22,
      "expRequired": 53000,
      "gainHP": 1,
      "gainAtk": 0,
      "gainSpAtk": 1,
      "gainDef": 0,
      "gainSpDef": 0,
      "fillA": 0
    },
    {
      "level": 23,
      "expRequired": 63000,
      "gainHP": 0,
      "gainAtk": 1,
      "gainSpAtk": 0,
      "gainDef": 1,
      "gainSpDef": 0,
      "fillA": 0
    },
    {
      "level": 24,
      "expRequired": 73000,
      "gainHP": 1,
      "gainAtk": 0,
      "gainSpAtk": 0,
      "gainDef": 0,
      "gainSpDef": 1,
      "fillA": 0
    },
    {
      "level": 25,
      "expRequired": 83000,
      "gainHP": 0,
      "gainAtk": 1,
      "gainSpAtk": 1,
      "gainDef": 0,
      "gainSpDef": 0,
      "fillA": 0
    },
    {
      "level": 26,
      "expRequired": 93000,
      "gainHP": 1,
      "gainAtk": 0,
      "gainSpAtk": 0,
      "gainDef": 1,
      "gainSpDef": 0,
      "fillA": 0
    },
    {
      "level": 27,
      "expRequired": 103000,
      "gainHP": 0,
      "gainAtk": 1,
      "gainSpAtk": 0,
      "gainDef": 0,
      "gainSpDef": 1,
      "fillA": 0
    },
    {
      "level": 28,
      "expRequired": 113000,
      "gainHP": 1,
      "gainAtk": 0,
      "gainSpAtk": 1,
      "gainDef": 0,
      "gainSpDef": 0,
      "fillA": 0
    },
    {
      "level": 29,
      "expRequired": 123000,
      "gainHP": 0,
      "gainAtk": 1,
      "gainSpAtk": 0,
      "gainDef": 1,
      "gainSpDef": 0,
      "fillA": 0
    },
    {
      "level": 30,
      "expRequired": 133000,
      "gainHP": 1,
      "gainAtk": 0,
      "gainSpAtk": 0,
      "gainDef": 0,
      "gainSpDef": 1,
      "fillA": 0
    },
    {
      "level": 31,
      "expRequired": 143000,
      "gainHP": 0,
      "gainAtk": 1,
      "gainSpAtk": 1,
      "gainDef": 0,
      "gainSpDef": 0,
      "fillA": 0
    },
    {
      "level": 32,
      "expRequired": 153000,
      "gainHP": 1,
      "gainAtk": 0,
      "gainSpAtk": 0,
      "gainDef": 1,
      "gainSpDef": 0,
      "fillA": 0
    },
    {
      "level": 33,
      "expRequired": 163000,
      "gainHP": 0,
      "gainAtk": 1,
      "gainSpAtk": 0,
      "gainDef": 0,
      "gainSpDef": 1,
      "fillA": 0
    },
    {
      "level": 34,
      "expRequired": 173000,
      "gainHP": 1,
      "gainAtk": 0,
      "gainSpAtk": 1,
      "gainDef": 0,
      "gainSpDef": 0,
      "fillA": 0
    },
    {
      "level": 35,
      "expRequired": 183000,
      "gainHP": 0,
      "gainAtk": 1,
      "gainSpAtk": 0,
      "gainDef": 1,
      "gainSpDef": 0,
      "fillA": 0
    },
    {
      "level": 36,
      "expRequired": 193000,
      "gainHP": 1,
      "gainAtk": 0,
      "gainSpAtk": 0,
      "gainDef": 0,
      "gainSpDef": 1,
      "fillA": 0
    },
    {
      "level": 37,
      "expRequired": 203000,
      "gainHP": 0,
      "gainAtk": 1,
      "gainSpAtk": 1,
      "gainDef": 0,
      "gainSpDef": 0,
      "fillA": 0
    },
    {
      "level": 38,
      "expRequired": 213000,
      "gainHP": 1,
      "gainAtk": 0,
      "gainSpAtk": 0,
      "gainDef": 1,
      "gainSpDef": 0,
      "fillA": 0
    },
    {
      "level": 39,
      "expRequired": 223000,
      "gainHP": 0,
      "gainAtk": 1,
      "gainSpAtk": 0,
      "gainDef": 0,
      "gainSpDef": 1,
      "fillA": 0
    },
    {
      "level": 40,
      "expRequired": 233000,
      "gainHP": 1,
      "gainAtk": 0,
      "gainSpAtk": 1,
      "gainDef": 0,
      "gainSpDef": 0,
      "fillA": 0
    },
    {
      "level": 41,
      "expRequired": 243000,
      "gainHP": 0,
      "gainAtk": 1,
      "gainSpAtk": 0,
      "gainDef": 1,
      "gainSpDef": 0,
      "fillA": 0
    },
    {
      "level": 42,
      "expRequired": 253000,
      "gainHP": 1,
      "gainAtk": 0,
      "gainSpAtk": 0,
      "gainDef": 0,
      "gainSpDef": 1,
      "fillA": 0
    },
    {
      "level": 43,
      "expRequired": 263000,
      "gainHP": 0,
      "gainAtk": 1,
      "gainSpAtk": 1,
      "gainDef": 0,
      "gainSpDef": 0,
      "fillA": 0
    },
    {
      "level": 44,
      "expRequired": 273000,
      "gainHP": 1,
      "gainAtk": 0,
      "gainSpAtk": 0,
      "gainDef": 1,
      "gainSpDef": 0,
      "fillA": 0
    },
    {
      "level": 45,
      "expRequired": 283000,
      "gainHP": 0,
      "gainAtk": 1,
      "gainSpAtk": 0,
      "gainDef": 0,
      "gainSpDef": 1,
      "fillA": 0
    },
    {
      "level": 46,
      "expRequired": 293000,
      "gainHP": 1,
      "gainAtk": 0,
      "gainSpAtk": 1,
      "gainDef": 0,
      "gainSpDef": 0,
      "fillA": 0
    },
    {
      "level": 47,
      "expRequired": 303000,
      "gainHP": 0,
      "gainAtk": 1,
      "gainSpAtk": 0,
      "gainDef": 1,
      "gainSpDef": 0,
      "fillA": 0
    },
    {
      "level": 48,
      "expRequired": 313000,
      "gainHP": 1,
      "gainAtk": 0,
      "gainSpAtk": 0,
      "gainDef": 0,
      "gainSpDef": 1,
      "fillA": 0
    },
    {
      "level": 49,
      "expRequired": 323000,
      "gainHP": 0,
      "gainAtk": 1,
      "gainSpAtk": 1,
      "gainDef": 0,
      "gainSpDef": 0,
      "fillA": 0
    },
    {
      "level": 50,
      "expRequired": 333000,
      "gainHP": 1,
      "gainAtk": 0,
      "gainSpAtk": 0,
      "gainDef": 1,
      "gainSpDef": 0,
      "fillA": 0
    },
    {
      "level": 51,
      "expRequired": 343000,
      "gainHP": 0,
      "gainAtk": 1,
      "gainSpAtk": 0,
      "gainDef": 0,
      "gainSpDef": 1,
      "fillA": 0
    },
    {
      "level": 52,
      "expRequired": 353000,
      "gainHP": 1,
      "gainAtk": 0,
      "gainSpAtk": 1,
      "gainDef": 0,
      "gainSpDef": 0,
      "fillA": 0
    },
    {
      "level": 53,
      "expRequired": 363000,
      "gainHP": 0,
      "gainAtk": 1,
      "gainSpAtk": 0,
      "gainDef": 1,
      "gainSpDef": 0,
      "fillA": 0
    },
    {
      "level": 54,
      "expRequired": 373000,
      "gainHP": 1,
      "gainAtk": 0,
      "gainSpAtk": 0,
      "gainDef": 0,
      "gainSpDef": 1,
      "fillA": 0
    },
    {
      "level": 55,
      "expRequired": 383000,
      "gainHP": 0,
      "gainAtk": 1,
      "gainSpAtk": 1,
      "gainDef": 0,
      "gainSpDef": 0,
      "fillA": 0
    },
    {
      "level": 56,
      "expRequired": 393000,
      "gainHP": 1,
      "gainAtk": 0,
      "gainSpAtk": 0,
      "gainDef": 1,
      "gainSpDef": 0,
      "fillA": 0
    },
    {
      "level": 57,
      "expRequired": 403000,
      "gainHP": 0,
      "gainAtk": 1,
      "gainSpAtk": 0,
      "gainDef": 0,
      "gainSpDef": 1,
      "fillA": 0
    },
    {
      "level": 58,
      "expRequired": 413000,
      "gainHP": 1,
      "gainAtk": 0,
      "gainSpAtk": 1,
      "gainDef": 0,
      "gainSpDef": 0,
      "fillA": 0
    },
    {
      "level": 59,
      "expRequired": 423000,
      "gainHP": 0,
      "gainAtk": 1,
      "gainSpAtk": 0,
      "gainDef": 1,
      "gainSpDef": 0,
      "fillA": 0
    },
    {
      "level": 60,
      "expRequired": 433000,
      "gainHP": 1,
      "gainAtk": 0,
      "gainSpAtk": 1,
      "gainDef": 0,
      "gainSpDef": 0,
      "fillA": 0
    },
    {
      "level": 61,
      "expRequired": 443000,
      "gainHP": 1,
      "gainAtk": 0,
      "gainSpAtk": 1,
      "gainDef": 0,
      "gainSpDef": 0,
      "fillA": 0
    },
    {
      "level": 62,
      "expRequired": 453000,
      "gainHP": 1,
      "gainAtk": 0,
      "gainSpAtk": 1,
      "gainDef": 0,
      "gainSpDef": 0,
      "fillA": 0
    },
    {
      "level": 63,
      "expRequired": 463000,
      "gainHP": 1,
      "gainAtk": 0,
      "gainSpAtk": 1,
      "gainDef": 0,
      "gainSpDef": 0,
      "fillA": 0
    },
    {
      "level": 64,
      "expRequired": 473000,
      "gainHP": 1,
      "gainAtk": 0,
      "gainSpAtk": 1,
      "gainDef": 0,
      "gainSpDef": 0,
      "fillA": 0
    },
    {
      "level": 65,
      "expRequired": 513000,
      "gainHP": 1,
      "gainAtk": 0,
      "gainSpAtk": 1,
      "gainDef": 0,
      "gainSpDef": 0,
      "fillA": 0
    },
    {
      "level": 66,
      "expRequired": 553000,
      "gainHP": 1,
      "gainAtk": 0,
      "gainSpAtk": 1,
      "gainDef": 0,
      "gainSpDef": 0,
      "fillA": 0
    },
    {
      "level": 67,
      "expRequired": 593000,
      "gainHP": 1,
      "gainAtk": 0,
      "gainSpAtk": 1,
      "gainDef": 0,
      "gainSpDef": 0,
      "fillA": 0
    },
    {
      "level": 68,
      "expRequired": 633000,
      "gainHP": 1,
      "gainAtk": 0,
      "gainSpAtk": 1,
      "gainDef": 0,
      "gainSpDef": 0,
      "fillA": 0
    },
    {
      "level": 69,
      "expRequired": 673000,
      "gainHP": 1,
      "gainAtk": 0,
      "gainSpAtk": 1,
      "gainDef": 0,
      "gainSpDef": 0,
      "fillA": 0
    },
    {
      "level": 70,
      "expRequired": 713000,
      "gainHP": 1,
      "gainAtk": 1,
      "gainSpAtk": 0,
      "gainDef": 0,
      "gainSpDef": 0,
      "fillA": 0
    },
    {
      "level": 71,
      "expRequired": 753000,
      "gainHP": 1,
      "gainAtk": 1,
      "gainSpAtk": 0,
      "gainDef": 0,
      "gainSpDef": 0,
      "fillA": 0
    },
    {
      "level": 72,
      "expRequired": 793000,
      "gainHP": 1,
      "gainAtk": 1,
      "gainSpAtk": 0,
      "gainDef": 0,
      "gainSpDef": 0,
      "fillA": 0
    },
    {
      "level": 73,
      "expRequired": 833000,
      "gainHP": 1,
      "gainAtk": 1,
      "gainSpAtk": 0,
      "gainDef": 0,
      "gainSpDef": 0,
      "fillA": 0
    },
    {
      "level": 74,
      "expRequired": 873000,
      "gainHP": 1,
      "gainAtk": 1,
      "gainSpAtk": 0,
      "gainDef": 0,
      "gainSpDef": 0,
      "fillA": 0
    },
    {
      "level": 75,
      "expRequired": 913000,
      "gainHP": 1,
      "gainAtk": 1,
      "gainSpAtk": 0,
      "gainDef": 0,
      "gainSpDef": 0,
      "fillA": 0
    },
    {
      "level": 76,
      "expRequired": 953000,
      "gainHP": 1,
      "gainAtk": 1,
      "gainSpAtk": 0,
      "gainDef": 0,
      "gainSpDef": 0,
      "fillA": 0
    },
    {
      "level": 77,
      "expRequired": 993000,
      "gainHP": 1,
      "gainAtk": 1,
      "gainSpAtk": 0,
      "gainDef": 0,
      "gainSpDef": 0,
      "fillA": 0
    },
    {
      "level": 78,
      "expRequired": 1033000,
      "gainHP": 1,
      "gainAtk": 1,
      "gainSpAtk": 0,
      "gainDef": 0,
      "gainSpDef": 0,
      "fillA": 0
    },
    {
      "level": 79,
      "expRequired": 1073000,
      "gainHP": 1,
      "gainAtk": 1,
      "gainSpAtk": 0,
      "gainDef": 0,
      "gainSpDef": 0,
      "fillA": 0
    },
    {
      "level": 80,
      "expRequired": 1113000,
      "gainHP": 1,
      "gainAtk": 0,
      "gainSpAtk": 1,
      "gainDef": 0,
      "gainSpDef": 0,
      "fillA": 0
    },
    {
      "level": 81,
      "expRequired": 1153000,
      "gainHP": 1,
      "gainAtk": 0,
      "gainSpAtk": 1,
      "gainDef": 0,
      "gainSpDef": 0,
      "fillA": 0
    },
    {
      "level": 82,
      "expRequired": 1193000,
      "gainHP": 1,
      "gainAtk": 0,
      "gainSpAtk": 1,
      "gainDef": 0,
      "gainSpDef": 0,
      "fillA": 0
    },
    {
      "level": 83,
      "expRequired": 1233000,
      "gainHP": 1,
      "gainAtk": 0,
      "gainSpAtk": 1,
      "gainDef": 0,
      "gainSpDef": 0,
      "fillA": 0
    },
    {
      "level": 84,
      "expRequired": 1273000,
      "gainHP": 1,
      "gainAtk": 0,
      "gainSpAtk": 1,
      "gainDef": 0,
      "gainSpDef": 0,
      "fillA": 0
    },
    {
      "level": 85,
      "expRequired": 1313000,
      "gainHP": 1,
      "gainAtk": 0,
      "gainSpAtk": 1,
      "gainDef": 0,
      "gainSpDef": 0,
      "fillA": 0
    },
    {
      "level": 86,
      "expRequired": 1353000,
      "gainHP": 1,
      "gainAtk": 0,
      "gainSpAtk": 1,
      "gainDef": 0,
      "gainSpDef": 0,
      "fillA": 0
    },
    {
      "level": 87,
      "expRequired": 1393000,
      "gainHP": 1,
      "gainAtk": 0,
      "gainSpAtk": 1,
      "gainDef": 0,
      "gainSpDef": 0,
      "fillA": 0
    },
    {
      "level": 88,
      "expRequired": 1433000,
      "gainHP": 1,
      "gainAtk": 0,
      "gainSpAtk": 1,
      "gainDef": 0,
      "gainSpDef": 0,
      "fillA": 0
    },
    {
      "level": 89,
      "expRequired": 1473000,
      "gainHP": 1,
      "gainAtk": 0,
      "gainSpAtk": 1,
      "gainDef": 0,
      "gainSpDef": 0,
      "fillA": 0
    },
    {
      "level": 90,
      "expRequired": 1513000,
      "gainHP": 1,
      "gainAtk": 1,
      "gainSpAtk": 1,
      "gainDef": 0,
      "gainSpDef": 0,
      "fillA": 0
    },
    {
      "level": 91,
      "expRequired": 1553000,
      "gainHP": 1,
      "gainAtk": 1,
      "gainSpAtk": 1,
      "gainDef": 0,
      "gainSpDef": 0,
      "fillA": 0
    },
    {
      "level": 92,
      "expRequired": 1593000,
      "gainHP": 1,
      "gainAtk": 1,
      "gainSpAtk": 1,
      "gainDef": 0,
      "gainSpDef": 0,
      "fillA": 0
    },
    {
      "level": 93,
      "expRequired": 1633000,
      "gainHP": 1,
      "gainAtk": 1,
      "gainSpAtk": 1,
      "gainDef": 0,
      "gainSpDef": 0,
      "fillA": 0
    },
    {
      "level": 94,
      "expRequired": 1673000,
      "gainHP": 1,
      "gainAtk": 1,
      "gainSpAtk": 1,
      "gainDef": 0,
      "gainSpDef": 0,
      "fillA": 0
    },
    {
      "level": 95,
      "expRequired": 1713000,
      "gainHP": 1,
      "gainAtk": 1,
      "gainSpAtk": 1,
      "gainDef": 0,
      "gainSpDef": 0,
      "fillA": 0
    },
    {
      "level": 96,
      "expRequired": 1753000,
      "gainHP": 1,
      "gainAtk": 1,
      "gainSpAtk": 1,
      "gainDef": 0,
      "gainSpDef": 0,
      "fillA": 0
    },
    {
      "level": 97,
      "expRequired": 1793000,
      "gainHP": 1,
      "gainAtk": 1,
      "gainSpAtk": 1,
      "gainDef": 0,
      "gainSpDef": 0,
      "fillA": 0
    },
    {
      "level": 98,
      "expRequired": 1833000,
      "gainHP": 1,
      "gainAtk": 1,
      "gainSpAtk": 1,
      "gainDef": 0,
      "gainSpDef": 0,
      "fillA": 0
    },
    {
      "level": 99,
      "expRequired": 1873000,
      "gainHP": 1,
      "gainAtk": 1,
      "gainSpAtk": 1,
      "gainDef": 0,
      "gainSpDef": 0,
      "fillA": 0
    },
    {
      "level": 100,
      "expRequired": 1913000,
      "gainHP": 1,
      "gainAtk": 1,
      "gainSpAtk": 1,
      "gainDef": 0,
      "gainSpDef": 0,
      "fillA": 0
    }
  ]
}
