{
  "archiveName": "lvmp100",
  "speciesId": 100,
  "recordCount": 100,
  "records": [
    {
      "level": 1,
      "expRequired": 0,
      "gainHP": 0,
      "gainAtk": 0,
      "gainSpAtk": 0,
      "gainDef": 0,
      "gainSpDef": 0,
      "fillA": 0
    },
    {
      "level": 2,
      "expRequired": 50,
      "gainHP": 1,
      "gainAtk": 1,
      "gainSpAtk": 1,
      "gainDef": 1,
      "gainSpDef": 1,
      "fillA": 0
    },
    {
      "level": 3,
      "expRequired": 100,
      "gainHP": 1,
      "gainAtk": 1,
      "gainSpAtk": 1,
      "gainDef": 0,
      "gainSpDef": 0,
      "fillA": 0
    },
    {
      "level": 4,
      "expRequired": 150,
      "gainHP": 3,
      "gainAtk": 2,
      "gainSpAtk": 2,
      "gainDef": 2,
      "gainSpDef": 2,
      "fillA": 0
    },
    {
      "level": 5,
      "expRequired": 350,
      "gainHP": 3,
      "gainAtk": 2,
      "gainSpAtk": 2,
      "gainDef": 2,
      "gainSpDef": 2,
      "fillA": 0
    },
    {
      "level": 6,
      "expRequired": 550,
      "gainHP": 3,
      "gainAtk": 2,
      "gainSpAtk": 2,
      "gainDef": 2,
      "gainSpDef": 2,
      "fillA": 0
    },
    {
      "level": 7,
      "expRequired": 850,
      "gainHP": 3,
      "gainAtk": 2,
      "gainSpAtk": 2,
      "gainDef": 2,
      "gainSpDef": 2,
      "fillA": 0
    },
    {
      "level": 8,
      "expRequired": 1150,
      "gainHP": 3,
      "gainAtk": 2,
      "gainSpAtk": 2,
      "gainDef": 2,
      "gainSpDef": 2,
      "fillA": 0
    },
    {
      "level": 9,
      "expRequired": 1550,
      "gainHP": 3,
      "gainAtk": 2,
      "gainSpAtk": 2,
      "gainDef": 2,
      "gainSpDef": 2,
      "fillA": 0
    },
    {
      "level": 10,
      "expRequired": 2000,
      "gainHP": 3,
      "gainAtk": 2,
      "gainSpAtk": 2,
      "gainDef": 1,
      "gainSpDef": 1,
      "fillA": 0
    },
    {
      "level": 11,
      "expRequired": 2500,
      "gainHP": 3,
      "gainAtk": 2,
      "gainSpAtk": 2,
      "gainDef": 1,
      "gainSpDef": 1,
      "fillA": 0
    },
    {
      "level": 12,
      "expRequired": 3064,
      "gainHP": 3,
      "gainAtk": 2,
      "gainSpAtk": 2,
      "gainDef": 1,
      "gainSpDef": 1,
      "fillA": 0
    },
    {
      "level": 13,
      "expRequired": 5764,
      "gainHP": 3,
      "gainAtk": 2,
      "gainSpAtk": 2,
      "gainDef": 1,
      "gainSpDef": 1,
      "fillA": 0
    },
    {
      "level": 14,
      "expRequired": 10004,
      "gainHP": 3,
      "gainAtk": 1,
      "gainSpAtk": 2,
      "gainDef": 1,
      "gainSpDef": 1,
      "fillA": 0
    },
    {
      "level": 15,
      "expRequired": 15004,
      "gainHP": 3,
      "gainAtk": 1,
      "gainSpAtk": 1,
      "gainDef": 1,
      "gainSpDef": 1,
      "fillA": 0
    },
    {
      "level": 16,
      "expRequired": 20404,
      "gainHP": 3,
      "gainAtk": 1,
      "gainSpAtk": 1,
      "gainDef": 1,
      "gainSpDef": 1,
      "fillA": 0
    },
    {
      "level": 17,
      "expRequired": 25804,
      "gainHP": 3,
      "gainAtk": 1,
      "gainSpAtk": 1,
      "gainDef": 1,
      "gainSpDef": 1,
      "fillA": 0
    },
    {
      "level": 18,
      "expRequired": 31804,
      "gainHP": 3,
      "gainAtk": 1,
      "gainSpAtk": 1,
      "gainDef": 1,
      "gainSpDef": 1,
      "fillA": 0
    },
    {
      "level": 19,
      "expRequired": 37804,
      "gainHP": 3,
      "gainAtk": 1,
      "gainSpAtk": 1,
      "gainDef": 1,
      "gainSpDef": 1,
      "fillA": 0
    },
    {
      "level": 20,
      "expRequired": 43804,
      "gainHP": 3,
      "gainAtk": 1,
      "gainSpAtk": 1,
      "gainDef": 1,
      "gainSpDef": 1,
      "fillA": 0
    },
    {
      "level": 21,
      "expRequired": 49804,
      "gainHP": 3,
      "gainAtk": 1,
      "gainSpAtk": 1,
      "gainDef": 1,
      "gainSpDef": 1,
      "fillA": 0
    },
    {
      "level": 22,
      "expRequired": 55804,
      "gainHP": 3,
      "gainAtk": 1,
      "gainSpAtk": 1,
      "gainDef": 1,
      "gainSpDef": 1,
      "fillA": 0
    },
    {
      "level": 23,
      "expRequired": 65000,
      "gainHP": 3,
      "gainAtk": 1,
      "gainSpAtk": 1,
      "gainDef": 1,
      "gainSpDef": 1,
      "fillA": 0
    },
    {
      "level": 24,
      "expRequired": 75000,
      "gainHP": 3,
      "gainAtk": 1,
      "gainSpAtk": 1,
      "gainDef": 1,
      "gainSpDef": 1,
      "fillA": 0
    },
    {
      "level": 25,
      "expRequired": 85000,
      "gainHP": 3,
      "gainAtk": 1,
      "gainSpAtk": 1,
      "gainDef": 1,
      "gainSpDef": 1,
      "fillA": 0
    },
    {
      "level": 26,
      "expRequired": 95000,
      "gainHP": 2,
      "gainAtk": 1,
      "gainSpAtk": 1,
      "gainDef": 1,
      "gainSpDef": 1,
      "fillA": 0
    },
    {
      "level": 27,
      "expRequired": 105000,
      "gainHP": 2,
      "gainAtk": 1,
      "gainSpAtk": 1,
      "gainDef": 1,
      "gainSpDef": 1,
      "fillA": 0
    },
    {
      "level": 28,
      "expRequired": 125000,
      "gainHP": 2,
      "gainAtk": 1,
      "gainSpAtk": 1,
      "gainDef": 1,
      "gainSpDef": 0,
      "fillA": 0
    },
    {
      "level": 29,
      "expRequired": 145000,
      "gainHP": 2,
      "gainAtk": 1,
      "gainSpAtk": 1,
      "gainDef": 0,
      "gainSpDef": 0,
      "fillA": 0
    },
    {
      "level": 30,
      "expRequired": 165000,
      "gainHP": 1,
      "gainAtk": 1,
      "gainSpAtk": 1,
      "gainDef": 0,
      "gainSpDef": 0,
      "fillA": 0
    },
    {
      "level": 31,
      "expRequired": 185000,
      "gainHP": 1,
      "gainAtk": 1,
      "gainSpAtk": 1,
      "gainDef": 1,
      "gainSpDef": 1,
      "fillA": 0
    },
    {
      "level": 32,
      "expRequired": 205000,
      "gainHP": 1,
      "gainAtk": 1,
      "gainSpAtk": 1,
      "gainDef": 0,
      "gainSpDef": 0,
      "fillA": 0
    },
    {
      "level": 33,
      "expRequired": 235000,
      "gainHP": 1,
      "gainAtk": 1,
      "gainSpAtk": 1,
      "gainDef": 1,
      "gainSpDef": 1,
      "fillA": 0
    },
    {
      "level": 34,
      "expRequired": 265000,
      "gainHP": 1,
      "gainAtk": 1,
      "gainSpAtk": 1,
      "gainDef": 1,
      "gainSpDef": 1,
      "fillA": 0
    },
    {
      "level": 35,
      "expRequired": 295000,
      "gainHP": 1,
      "gainAtk": 1,
      "gainSpAtk": 1,
      "gainDef": 0,
      "gainSpDef": 0,
      "fillA": 0
    },
    {
      "level": 36,
      "expRequired": 325000,
      "gainHP": 1,
      "gainAtk": 1,
      "gainSpAtk": 1,
      "gainDef": 1,
      "gainSpDef": 1,
      "fillA": 0
    },
    {
      "level": 37,
      "expRequired": 355000,
      "gainHP": 1,
      "gainAtk": 1,
      "gainSpAtk": 1,
      "gainDef": 0,
      "gainSpDef": 0,
      "fillA": 0
    },
    {
      "level": 38,
      "expRequired": 385000,
      "gainHP": 1,
      "gainAtk": 1,
      "gainSpAtk": 1,
      "gainDef": 1,
      "gainSpDef": 1,
      "fillA": 0
    },
    {
      "level": 39,
      "expRequired": 415000,
      "gainHP": 1,
      "gainAtk": 1,
      "gainSpAtk": 1,
      "gainDef": 1,
      "gainSpDef": 1,
      "fillA": 0
    },
    {
      "level": 40,
      "expRequired": 445000,
      "gainHP": 1,
      "gainAtk": 0,
      "gainSpAtk": 1,
      "gainDef": 0,
      "gainSpDef": 1,
      "fillA": 0
    },
    {
      "level": 41,
      "expRequired": 475000,
      "gainHP": 0,
      "gainAtk": 1,
      "gainSpAtk": 0,
      "gainDef": 1,
      "gainSpDef": 0,
      "fillA": 0
    },
    {
      "level": 42,
      "expRequired": 505000,
      "gainHP": 1,
      "gainAtk": 0,
      "gainSpAtk": 1,
      "gainDef": 0,
      "gainSpDef": 1,
      "fillA": 0
    },
    {
      "level": 43,
      "expRequired": 535000,
      "gainHP": 0,
      "gainAtk": 1,
      "gainSpAtk": 0,
      "gainDef": 1,
      "gainSpDef": 0,
      "fillA": 0
    },
    {
      "level": 44,
      "expRequired": 565000,
      "gainHP": 1,
      "gainAtk": 0,
      "gainSpAtk": 1,
      "gainDef": 0,
      "gainSpDef": 1,
      "fillA": 0
    },
    {
      "level": 45,
      "expRequired": 595000,
      "gainHP": 0,
      "gainAtk": 1,
      "gainSpAtk": 0,
      "gainDef": 1,
      "gainSpDef": 0,
      "fillA": 0
    },
    {
      "level": 46,
      "expRequired": 625000,
      "gainHP": 1,
      "gainAtk": 0,
      "gainSpAtk": 1,
      "gainDef": 0,
      "gainSpDef": 1,
      "fillA": 0
    },
    {
      "level": 47,
      "expRequired": 655000,
      "gainHP": 0,
      "gainAtk": 1,
      "gainSpAtk": 0,
      "gainDef": 1,
      "gainSpDef": 0,
      "fillA": 0
    },
    {
      "level": 48,
      "expRequired": 685000,
      "gainHP": 1,
      "gainAtk": 0,
      "gainSpAtk": 1,
      "gainDef": 0,
      "gainSpDef": 1,
      "fillA": 0
    },
    {
      "level": 49,
      "expRequired": 715000,
      "gainHP": 0,
      "gainAtk": 1,
      "gainSpAtk": 0,
      "gainDef": 1,
      "gainSpDef": 0,
      "fillA": 0
    },
    {
      "level": 50,
      "expRequired": 745000,
      "gainHP": 0,
      "gainAtk": 0,
      "gainSpAtk": 1,
      "gainDef": 0,
      "gainSpDef": 1,
      "fillA": 0
    },
    {
      "level": 51,
      "expRequired": 775000,
      "gainHP": 0,
      "gainAtk": 1,
      "gainSpAtk": 0,
      "gainDef": 1,
      "gainSpDef": 0,
      "fillA": 0
    },
    {
      "level": 52,
      "expRequired": 805000,
      "gainHP": 0,
      "gainAtk": 0,
      "gainSpAtk": 1,
      "gainDef": 0,
      "gainSpDef": 1,
      "fillA": 0
    },
    {
      "level": 53,
      "expRequired": 835000,
      "gainHP": 0,
      "gainAtk": 1,
      "gainSpAtk": 0,
      "gainDef": 1,
      "gainSpDef": 0,
      "fillA": 0
    },
    {
      "level": 54,
      "expRequired": 865000,
      "gainHP": 0,
      "gainAtk": 0,
      "gainSpAtk": 1,
      "gainDef": 0,
      "gainSpDef": 1,
      "fillA": 0
    },
    {
      "level": 55,
      "expRequired": 895000,
      "gainHP": 0,
      "gainAtk": 1,
      "gainSpAtk": 0,
      "gainDef": 1,
      "gainSpDef": 0,
      "fillA": 0
    },
    {
      "level": 56,
      "expRequired": 925000,
      "gainHP": 0,
      "gainAtk": 0,
      "gainSpAtk": 1,
      "gainDef": 0,
      "gainSpDef": 1,
      "fillA": 0
    },
    {
      "level": 57,
      "expRequired": 955000,
      "gainHP": 0,
      "gainAtk": 1,
      "gainSpAtk": 0,
      "gainDef": 1,
      "gainSpDef": 0,
      "fillA": 0
    },
    {
      "level": 58,
      "expRequired": 985000,
      "gainHP": 0,
      "gainAtk": 0,
      "gainSpAtk": 1,
      "gainDef": 0,
      "gainSpDef": 1,
      "fillA": 0
    },
    {
      "level": 59,
      "expRequired": 1015000,
      "gainHP": 0,
      "gainAtk": 1,
      "gainSpAtk": 0,
      "gainDef": 1,
      "gainSpDef": 0,
      "fillA": 0
    },
    {
      "level": 60,
      "expRequired": 1045000,
      "gainHP": 1,
      "gainAtk": 0,
      "gainSpAtk": 1,
      "gainDef": 0,
      "gainSpDef": 0,
      "fillA": 0
    },
    {
      "level": 61,
      "expRequired": 1075000,
      "gainHP": 1,
      "gainAtk": 0,
      "gainSpAtk": 1,
      "gainDef": 0,
      "gainSpDef": 0,
      "fillA": 0
    },
    {
      "level": 62,
      "expRequired": 1105000,
      "gainHP": 1,
      "gainAtk": 0,
      "gainSpAtk": 1,
      "gainDef": 0,
      "gainSpDef": 0,
      "fillA": 0
    },
    {
      "level": 63,
      "expRequired": 1135000,
      "gainHP": 1,
      "gainAtk": 0,
      "gainSpAtk": 1,
      "gainDef": 0,
      "gainSpDef": 0,
      "fillA": 0
    },
    {
      "level": 64,
      "expRequired": 1165000,
      "gainHP": 1,
      "gainAtk": 0,
      "gainSpAtk": 1,
      "gainDef": 0,
      "gainSpDef": 0,
      "fillA": 0
    },
    {
      "level": 65,
      "expRequired": 1195000,
      "gainHP": 1,
      "gainAtk": 0,
      "gainSpAtk": 1,
      "gainDef": 0,
      "gainSpDef": 0,
      "fillA": 0
    },
    {
      "level": 66,
      "expRequired": 1225000,
      "gainHP": 1,
      "gainAtk": 0,
      "gainSpAtk": 1,
      "gainDef": 0,
      "gainSpDef": 0,
      "fillA": 0
    },
    {
      "level": 67,
      "expRequired": 1255000,
      "gainHP": 1,
      "gainAtk": 0,
      "gainSpAtk": 1,
      "gainDef": 0,
      "gainSpDef": 0,
      "fillA": 0
    },
    {
      "level": 68,
      "expRequired": 1285000,
      "gainHP": 1,
      "gainAtk": 0,
      "gainSpAtk": 1,
      "gainDef": 0,
      "gainSpDef": 0,
      "fillA": 0
    },
    {
      "level": 69,
      "expRequired": 1315000,
      "gainHP": 1,
      "gainAtk": 0,
      "gainSpAtk": 1,
      "gainDef": 0,
      "gainSpDef": 0,
      "fillA": 0
    },
    {
      "level": 70,
      "expRequired": 1345000,
      "gainHP": 1,
      "gainAtk": 1,
      "gainSpAtk": 0,
      "gainDef": 0,
      "gainSpDef": 0,
      "fillA": 0
    },
    {
      "level": 71,
      "expRequired": 1405000,
      "gainHP": 1,
      "gainAtk": 1,
      "gainSpAtk": 0,
      "gainDef": 0,
      "gainSpDef": 0,
      "fillA": 0
    },
    {
      "level": 72,
      "expRequired": 1465000,
      "gainHP": 1,
      "gainAtk": 1,
      "gainSpAtk": 0,
      "gainDef": 0,
      "gainSpDef": 0,
      "fillA": 0
    },
    {
      "level": 73,
      "expRequired": 1525000,
      "gainHP": 1,
      "gainAtk": 1,
      "gainSpAtk": 0,
      "gainDef": 0,
      "gainSpDef": 0,
      "fillA": 0
    },
    {
      "level": 74,
      "expRequired": 1585000,
      "gainHP": 1,
      "gainAtk": 1,
      "gainSpAtk": 0,
      "gainDef": 0,
      "gainSpDef": 0,
      "fillA": 0
    },
    {
      "level": 75,
      "expRequired": 1645000,
      "gainHP": 1,
      "gainAtk": 1,
      "gainSpAtk": 0,
      "gainDef": 0,
      "gainSpDef": 0,
      "fillA": 0
    },
    {
      "level": 76,
      "expRequired": 1705000,
      "gainHP": 1,
      "gainAtk": 1,
      "gainSpAtk": 0,
      "gainDef": 0,
      "gainSpDef": 0,
      "fillA": 0
    },
    {
      "level": 77,
      "expRequired": 1765000,
      "gainHP": 1,
      "gainAtk": 1,
      "gainSpAtk": 0,
      "gainDef": 0,
      "gainSpDef": 0,
      "fillA": 0
    },
    {
      "level": 78,
      "expRequired": 1825000,
      "gainHP": 1,
      "gainAtk": 1,
      "gainSpAtk": 0,
      "gainDef": 0,
      "gainSpDef": 0,
      "fillA": 0
    },
    {
      "level": 79,
      "expRequired": 1885000,
      "gainHP": 1,
      "gainAtk": 1,
      "gainSpAtk": 0,
      "gainDef": 0,
      "gainSpDef": 0,
      "fillA": 0
    },
    {
      "level": 80,
      "expRequired": 1945000,
      "gainHP": 1,
      "gainAtk": 0,
      "gainSpAtk": 1,
      "gainDef": 0,
      "gainSpDef": 0,
      "fillA": 0
    },
    {
      "level": 81,
      "expRequired": 2005000,
      "gainHP": 1,
      "gainAtk": 0,
      "gainSpAtk": 1,
      "gainDef": 0,
      "gainSpDef": 0,
      "fillA": 0
    },
    {
      "level": 82,
      "expRequired": 2065000,
      "gainHP": 1,
      "gainAtk": 0,
      "gainSpAtk": 1,
      "gainDef": 0,
      "gainSpDef": 0,
      "fillA": 0
    },
    {
      "level": 83,
      "expRequired": 2125000,
      "gainHP": 1,
      "gainAtk": 0,
      "gainSpAtk": 1,
      "gainDef": 0,
      "gainSpDef": 0,
      "fillA": 0
    },
    {
      "level": 84,
      "expRequired": 2185000,
      "gainHP": 1,
      "gainAtk": 0,
      "gainSpAtk": 1,
      "gainDef": 0,
      "gainSpDef": 0,
      "fillA": 0
    },
    {
      "level": 85,
      "expRequired": 2245000,
      "gainHP": 1,
      "gainAtk": 0,
      "gainSpAtk": 1,
      "gainDef": 0,
      "gainSpDef": 0,
      "fillA": 0
    },
    {
      "level": 86,
      "expRequired": 2305000,
      "gainHP": 1,
      "gainAtk": 0,
      "gainSpAtk": 1,
      "gainDef": 0,
      "gainSpDef": 0,
      "fillA": 0
    },
    {
      "level": 87,
      "expRequired": 2365000,
      "gainHP": 1,
      "gainAtk": 0,
      "gainSpAtk": 1,
      "gainDef": 0,
      "gainSpDef": 0,
      "fillA": 0
    },
    {
      "level": 88,
      "expRequired": 2425000,
      "gainHP": 1,
      "gainAtk": 0,
      "gainSpAtk": 1,
      "gainDef": 0,
      "gainSpDef": 0,
      "fillA": 0
    },
    {
      "level": 89,
      "expRequired": 2485000,
      "gainHP": 1,
      "gainAtk": 0,
      "gainSpAtk": 1,
      "gainDef": 0,
      "gainSpDef": 0,
      "fillA": 0
    },
    {
      "level": 90,
      "expRequired": 2545000,
      "gainHP": 1,
      "gainAtk": 1,
      "gainSpAtk": 1,
      "gainDef": 0,
      "gainSpDef": 0,
      "fillA": 0
    },
    {
      "level": 91,
      "expRequired": 2605000,
      "gainHP": 1,
      "gainAtk": 1,
      "gainSpAtk": 1,
      "gainDef": 0,
      "gainSpDef": 0,
      "fillA": 0
    },
    {
      "level": 92,
      "expRequired": 2665000,
      "gainHP": 1,
      "gainAtk": 1,
      "gainSpAtk": 1,
      "gainDef": 0,
      "gainSpDef": 0,
      "fillA": 0
    },
    {
      "level": 93,
      "expRequired": 2725000,
      "gainHP": 1,
      "gainAtk": 1,
      "gainSpAtk": 1,
      "gainDef": 0,
      "gainSpDef": 0,
      "fillA": 0
    },
    {
      "level": 94,
      "expRequired": 2785000,
      "gainHP": 1,
      "gainAtk": 1,
      "gainSpAtk": 1,
      "gainDef": 0,
      "gainSpDef": 0,
      "fillA": 0
    },
    {
      "level": 95,
      "expRequired": 2845000,
      "gainHP": 1,
      "gainAtk": 1,
      "gainSpAtk": 1,
      "gainDef": 0,
      "gainSpDef": 0,
      "fillA": 0
    },
    {
      "level": 96,
      "expRequired": 2905000,
      "gainHP": 1,
      "gainAtk": 1,
      "gainSpAtk": 1,
      "gainDef": 0,
      "gainSpDef": 0,
      "fillA": 0
    },
    {
      "level": 97,
      "expRequired": 2965000,
      "gainHP": 1,
      "gainAtk": 1,
      "gainSpAtk": 1,
      "gainDef": 0,
      "gainSpDef": 0,
      "fillA": 0
    },
    {
      "level": 98,
      "expRequired": 3025000,
      "gainHP": 1,
      "gainAtk": 1,
      "gainSpAtk": 1,
      "gainDef": 0,
      "gainSpDef": 0,
      "fillA": 0
    },
    {
      "level": 99,
      "expRequired": 3085000,
      "gainHP": 1,
      "gainAtk": 1,
      "gainSpAtk": 1,
      "gainDef": 0,
      "gainSpDef": 0,
      "fillA": 0
    },
    {
      "level": 100,
      "expRequired": 3145000,
      "gainHP": 1,
      "gainAtk": 1,
      "gainSpAtk": 1,
      "gainDef": 0,
      "gainSpDef": 0,
      "fillA": 0
    }
  ]
}
