{
  "archiveName": "lvmp363",
  "speciesId": 363,
  "recordCount": 100,
  "records": [
    {
      "level": 1,
      "expRequired": 0,
      "gainHP": 0,
      "gainAtk": 0,
      "gainSpAtk": 0,
      "gainDef": 0,
      "gainSpDef": 0,
      "fillA": 0
    },
    {
      "level": 2,
      "expRequired": 360,
      "gainHP": 2,
      "gainAtk": 1,
      "gainSpAtk": 1,
      "gainDef": 1,
      "gainSpDef": 1,
      "fillA": 0
    },
    {
      "level": 3,
      "expRequired": 760,
      "gainHP": 2,
      "gainAtk": 1,
      "gainSpAtk": 1,
      "gainDef": 0,
      "gainSpDef": 0,
      "fillA": 0
    },
    {
      "level": 4,
      "expRequired": 1760,
      "gainHP": 2,
      "gainAtk": 0,
      "gainSpAtk": 0,
      "gainDef": 1,
      "gainSpDef": 1,
      "fillA": 0
    },
    {
      "level": 5,
      "expRequired": 2760,
      "gainHP": 2,
      "gainAtk": 1,
      "gainSpAtk": 1,
      "gainDef": 0,
      "gainSpDef": 0,
      "fillA": 0
    },
    {
      "level": 6,
      "expRequired": 4760,
      "gainHP": 2,
      "gainAtk": 0,
      "gainSpAtk": 0,
      "gainDef": 1,
      "gainSpDef": 1,
      "fillA": 0
    },
    {
      "level": 7,
      "expRequired": 7000,
      "gainHP": 2,
      "gainAtk": 1,
      "gainSpAtk": 1,
      "gainDef": 0,
      "gainSpDef": 0,
      "fillA": 0
    },
    {
      "level": 8,
      "expRequired": 9240,
      "gainHP": 2,
      "gainAtk": 1,
      "gainSpAtk": 1,
      "gainDef": 1,
      "gainSpDef": 1,
      "fillA": 0
    },
    {
      "level": 9,
      "expRequired": 12240,
      "gainHP": 2,
      "gainAtk": 1,
      "gainSpAtk": 1,
      "gainDef": 0,
      "gainSpDef": 0,
      "fillA": 0
    },
    {
      "level": 10,
      "expRequired": 15440,
      "gainHP": 2,
      "gainAtk": 1,
      "gainSpAtk": 1,
      "gainDef": 1,
      "gainSpDef": 1,
      "fillA": 0
    },
    {
      "level": 11,
      "expRequired": 19040,
      "gainHP": 2,
      "gainAtk": 1,
      "gainSpAtk": 1,
      "gainDef": 0,
      "gainSpDef": 0,
      "fillA": 0
    },
    {
      "level": 12,
      "expRequired": 22640,
      "gainHP": 2,
      "gainAtk": 1,
      "gainSpAtk": 1,
      "gainDef": 1,
      "gainSpDef": 1,
      "fillA": 0
    },
    {
      "level": 13,
      "expRequired": 26240,
      "gainHP": 2,
      "gainAtk": 1,
      "gainSpAtk": 1,
      "gainDef": 0,
      "gainSpDef": 0,
      "fillA": 0
    },
    {
      "level": 14,
      "expRequired": 30040,
      "gainHP": 2,
      "gainAtk": 1,
      "gainSpAtk": 1,
      "gainDef": 0,
      "gainSpDef": 0,
      "fillA": 0
    },
    {
      "level": 15,
      "expRequired": 35040,
      "gainHP": 2,
      "gainAtk": 1,
      "gainSpAtk": 1,
      "gainDef": 1,
      "gainSpDef": 1,
      "fillA": 0
    },
    {
      "level": 16,
      "expRequired": 40040,
      "gainHP": 2,
      "gainAtk": 1,
      "gainSpAtk": 1,
      "gainDef": 1,
      "gainSpDef": 1,
      "fillA": 0
    },
    {
      "level": 17,
      "expRequired": 45040,
      "gainHP": 2,
      "gainAtk": 1,
      "gainSpAtk": 1,
      "gainDef": 0,
      "gainSpDef": 0,
      "fillA": 0
    },
    {
      "level": 18,
      "expRequired": 52040,
      "gainHP": 2,
      "gainAtk": 1,
      "gainSpAtk": 1,
      "gainDef": 1,
      "gainSpDef": 1,
      "fillA": 0
    },
    {
      "level": 19,
      "expRequired": 59040,
      "gainHP": 2,
      "gainAtk": 1,
      "gainSpAtk": 1,
      "gainDef": 0,
      "gainSpDef": 0,
      "fillA": 0
    },
    {
      "level": 20,
      "expRequired": 66040,
      "gainHP": 2,
      "gainAtk": 1,
      "gainSpAtk": 1,
      "gainDef": 1,
      "gainSpDef": 1,
      "fillA": 0
    },
    {
      "level": 21,
      "expRequired": 76040,
      "gainHP": 1,
      "gainAtk": 1,
      "gainSpAtk": 1,
      "gainDef": 0,
      "gainSpDef": 0,
      "fillA": 0
    },
    {
      "level": 22,
      "expRequired": 86040,
      "gainHP": 2,
      "gainAtk": 1,
      "gainSpAtk": 1,
      "gainDef": 1,
      "gainSpDef": 1,
      "fillA": 0
    },
    {
      "level": 23,
      "expRequired": 96040,
      "gainHP": 1,
      "gainAtk": 1,
      "gainSpAtk": 1,
      "gainDef": 0,
      "gainSpDef": 0,
      "fillA": 0
    },
    {
      "level": 24,
      "expRequired": 106040,
      "gainHP": 2,
      "gainAtk": 1,
      "gainSpAtk": 1,
      "gainDef": 1,
      "gainSpDef": 1,
      "fillA": 0
    },
    {
      "level": 25,
      "expRequired": 121040,
      "gainHP": 1,
      "gainAtk": 1,
      "gainSpAtk": 1,
      "gainDef": 0,
      "gainSpDef": 0,
      "fillA": 0
    },
    {
      "level": 26,
      "expRequired": 136040,
      "gainHP": 1,
      "gainAtk": 1,
      "gainSpAtk": 1,
      "gainDef": 1,
      "gainSpDef": 1,
      "fillA": 0
    },
    {
      "level": 27,
      "expRequired": 156040,
      "gainHP": 1,
      "gainAtk": 1,
      "gainSpAtk": 1,
      "gainDef": 0,
      "gainSpDef": 0,
      "fillA": 0
    },
    {
      "level": 28,
      "expRequired": 176040,
      "gainHP": 1,
      "gainAtk": 1,
      "gainSpAtk": 1,
      "gainDef": 1,
      "gainSpDef": 1,
      "fillA": 0
    },
    {
      "level": 29,
      "expRequired": 196040,
      "gainHP": 1,
      "gainAtk": 1,
      "gainSpAtk": 1,
      "gainDef": 0,
      "gainSpDef": 0,
      "fillA": 0
    },
    {
      "level": 30,
      "expRequired": 216040,
      "gainHP": 1,
      "gainAtk": 1,
      "gainSpAtk": 1,
      "gainDef": 0,
      "gainSpDef": 0,
      "fillA": 0
    },
    {
      "level": 31,
      "expRequired": 236040,
      "gainHP": 1,
      "gainAtk": 1,
      "gainSpAtk": 1,
      "gainDef": 1,
      "gainSpDef": 1,
      "fillA": 0
    },
    {
      "level": 32,
      "expRequired": 266040,
      "gainHP": 1,
      "gainAtk": 1,
      "gainSpAtk": 1,
      "gainDef": 0,
      "gainSpDef": 0,
      "fillA": 0
    },
    {
      "level": 33,
      "expRequired": 296040,
      "gainHP": 1,
      "gainAtk": 1,
      "gainSpAtk": 1,
      "gainDef": 1,
      "gainSpDef": 1,
      "fillA": 0
    },
    {
      "level": 34,
      "expRequired": 326040,
      "gainHP": 1,
      "gainAtk": 1,
      "gainSpAtk": 1,
      "gainDef": 1,
      "gainSpDef": 1,
      "fillA": 0
    },
    {
      "level": 35,
      "expRequired": 356040,
      "gainHP": 1,
      "gainAtk": 1,
      "gainSpAtk": 1,
      "gainDef": 0,
      "gainSpDef": 0,
      "fillA": 0
    },
    {
      "level": 36,
      "expRequired": 386040,
      "gainHP": 1,
      "gainAtk": 1,
      "gainSpAtk": 1,
      "gainDef": 1,
      "gainSpDef": 1,
      "fillA": 0
    },
    {
      "level": 37,
      "expRequired": 416040,
      "gainHP": 1,
      "gainAtk": 1,
      "gainSpAtk": 1,
      "gainDef": 0,
      "gainSpDef": 0,
      "fillA": 0
    },
    {
      "level": 38,
      "expRequired": 446040,
      "gainHP": 1,
      "gainAtk": 1,
      "gainSpAtk": 1,
      "gainDef": 1,
      "gainSpDef": 1,
      "fillA": 0
    },
    {
      "level": 39,
      "expRequired": 476040,
      "gainHP": 1,
      "gainAtk": 1,
      "gainSpAtk": 1,
      "gainDef": 1,
      "gainSpDef": 1,
      "fillA": 0
    },
    {
      "level": 40,
      "expRequired": 506040,
      "gainHP": 1,
      "gainAtk": 0,
      "gainSpAtk": 1,
      "gainDef": 0,
      "gainSpDef": 1,
      "fillA": 0
    },
    {
      "level": 41,
      "expRequired": 536040,
      "gainHP": 0,
      "gainAtk": 1,
      "gainSpAtk": 0,
      "gainDef": 1,
      "gainSpDef": 0,
      "fillA": 0
    },
    {
      "level": 42,
      "expRequired": 566040,
      "gainHP": 1,
      "gainAtk": 0,
      "gainSpAtk": 1,
      "gainDef": 0,
      "gainSpDef": 1,
      "fillA": 0
    },
    {
      "level": 43,
      "expRequired": 596040,
      "gainHP": 0,
      "gainAtk": 1,
      "gainSpAtk": 0,
      "gainDef": 1,
      "gainSpDef": 0,
      "fillA": 0
    },
    {
      "level": 44,
      "expRequired": 626040,
      "gainHP": 1,
      "gainAtk": 0,
      "gainSpAtk": 1,
      "gainDef": 0,
      "gainSpDef": 1,
      "fillA": 0
    },
    {
      "level": 45,
      "expRequired": 656040,
      "gainHP": 0,
      "gainAtk": 1,
      "gainSpAtk": 0,
      "gainDef": 1,
      "gainSpDef": 0,
      "fillA": 0
    },
    {
      "level": 46,
      "expRequired": 686040,
      "gainHP": 1,
      "gainAtk": 0,
      "gainSpAtk": 1,
      "gainDef": 0,
      "gainSpDef": 1,
      "fillA": 0
    },
    {
      "level": 47,
      "expRequired": 716040,
      "gainHP": 0,
      "gainAtk": 1,
      "gainSpAtk": 0,
      "gainDef": 1,
      "gainSpDef": 0,
      "fillA": 0
    },
    {
      "level": 48,
      "expRequired": 746040,
      "gainHP": 1,
      "gainAtk": 0,
      "gainSpAtk": 1,
      "gainDef": 0,
      "gainSpDef": 1,
      "fillA": 0
    },
    {
      "level": 49,
      "expRequired": 776040,
      "gainHP": 0,
      "gainAtk": 1,
      "gainSpAtk": 0,
      "gainDef": 1,
      "gainSpDef": 0,
      "fillA": 0
    },
    {
      "level": 50,
      "expRequired": 806040,
      "gainHP": 1,
      "gainAtk": 0,
      "gainSpAtk": 1,
      "gainDef": 0,
      "gainSpDef": 1,
      "fillA": 0
    },
    {
      "level": 51,
      "expRequired": 836040,
      "gainHP": 0,
      "gainAtk": 1,
      "gainSpAtk": 0,
      "gainDef": 1,
      "gainSpDef": 0,
      "fillA": 0
    },
    {
      "level": 52,
      "expRequired": 866040,
      "gainHP": 1,
      "gainAtk": 0,
      "gainSpAtk": 1,
      "gainDef": 0,
      "gainSpDef": 1,
      "fillA": 0
    },
    {
      "level": 53,
      "expRequired": 896040,
      "gainHP": 0,
      "gainAtk": 1,
      "gainSpAtk": 0,
      "gainDef": 1,
      "gainSpDef": 0,
      "fillA": 0
    },
    {
      "level": 54,
      "expRequired": 926040,
      "gainHP": 1,
      "gainAtk": 0,
      "gainSpAtk": 1,
      "gainDef": 0,
      "gainSpDef": 1,
      "fillA": 0
    },
    {
      "level": 55,
      "expRequired": 956040,
      "gainHP": 0,
      "gainAtk": 1,
      "gainSpAtk": 0,
      "gainDef": 1,
      "gainSpDef": 0,
      "fillA": 0
    },
    {
      "level": 56,
      "expRequired": 986040,
      "gainHP": 1,
      "gainAtk": 0,
      "gainSpAtk": 1,
      "gainDef": 0,
      "gainSpDef": 1,
      "fillA": 0
    },
    {
      "level": 57,
      "expRequired": 1016040,
      "gainHP": 0,
      "gainAtk": 1,
      "gainSpAtk": 0,
      "gainDef": 1,
      "gainSpDef": 0,
      "fillA": 0
    },
    {
      "level": 58,
      "expRequired": 1046040,
      "gainHP": 1,
      "gainAtk": 0,
      "gainSpAtk": 1,
      "gainDef": 0,
      "gainSpDef": 1,
      "fillA": 0
    },
    {
      "level": 59,
      "expRequired": 1076040,
      "gainHP": 0,
      "gainAtk": 1,
      "gainSpAtk": 0,
      "gainDef": 1,
      "gainSpDef": 0,
      "fillA": 0
    },
    {
      "level": 60,
      "expRequired": 1106040,
      "gainHP": 1,
      "gainAtk": 0,
      "gainSpAtk": 1,
      "gainDef": 0,
      "gainSpDef": 0,
      "fillA": 0
    },
    {
      "level": 61,
      "expRequired": 1136040,
      "gainHP": 1,
      "gainAtk": 0,
      "gainSpAtk": 1,
      "gainDef": 0,
      "gainSpDef": 0,
      "fillA": 0
    },
    {
      "level": 62,
      "expRequired": 1166040,
      "gainHP": 1,
      "gainAtk": 0,
      "gainSpAtk": 1,
      "gainDef": 0,
      "gainSpDef": 0,
      "fillA": 0
    },
    {
      "level": 63,
      "expRequired": 1196040,
      "gainHP": 1,
      "gainAtk": 0,
      "gainSpAtk": 1,
      "gainDef": 0,
      "gainSpDef": 0,
      "fillA": 0
    },
    {
      "level": 64,
      "expRequired": 1226040,
      "gainHP": 1,
      "gainAtk": 0,
      "gainSpAtk": 1,
      "gainDef": 0,
      "gainSpDef": 0,
      "fillA": 0
    },
    {
      "level": 65,
      "expRequired": 1256040,
      "gainHP": 1,
      "gainAtk": 0,
      "gainSpAtk": 1,
      "gainDef": 0,
      "gainSpDef": 0,
      "fillA": 0
    },
    {
      "level": 66,
      "expRequired": 1286040,
      "gainHP": 1,
      "gainAtk": 0,
      "gainSpAtk": 1,
      "gainDef": 0,
      "gainSpDef": 0,
      "fillA": 0
    },
    {
      "level": 67,
      "expRequired": 1316040,
      "gainHP": 1,
      "gainAtk": 0,
      "gainSpAtk": 1,
      "gainDef": 0,
      "gainSpDef": 0,
      "fillA": 0
    },
    {
      "level": 68,
      "expRequired": 1346040,
      "gainHP": 1,
      "gainAtk": 0,
      "gainSpAtk": 1,
      "gainDef": 0,
      "gainSpDef": 0,
      "fillA": 0
    },
    {
      "level": 69,
      "expRequired": 1376040,
      "gainHP": 1,
      "gainAtk": 0,
      "gainSpAtk": 1,
      "gainDef": 0,
      "gainSpDef": 0,
      "fillA": 0
    },
    {
      "level": 70,
      "expRequired": 1406040,
      "gainHP": 1,
      "gainAtk": 1,
      "gainSpAtk": 0,
      "gainDef": 0,
      "gainSpDef": 0,
      "fillA": 0
    },
    {
      "level": 71,
      "expRequired": 1436040,
      "gainHP": 1,
      "gainAtk": 1,
      "gainSpAtk": 0,
      "gainDef": 0,
      "gainSpDef": 0,
      "fillA": 0
    },
    {
      "level": 72,
      "expRequired": 1466040,
      "gainHP": 1,
      "gainAtk": 1,
      "gainSpAtk": 0,
      "gainDef": 0,
      "gainSpDef": 0,
      "fillA": 0
    },
    {
      "level": 73,
      "expRequired": 1496040,
      "gainHP": 1,
      "gainAtk": 1,
      "gainSpAtk": 0,
      "gainDef": 0,
      "gainSpDef": 0,
      "fillA": 0
    },
    {
      "level": 74,
      "expRequired": 1526040,
      "gainHP": 1,
      "gainAtk": 1,
      "gainSpAtk": 0,
      "gainDef": 0,
      "gainSpDef": 0,
      "fillA": 0
    },
    {
      "level": 75,
      "expRequired": 1556040,
      "gainHP": 1,
      "gainAtk": 1,
      "gainSpAtk": 0,
      "gainDef": 0,
      "gainSpDef": 0,
      "fillA": 0
    },
    {
      "level": 76,
      "expRequired": 1586040,
      "gainHP": 1,
      "gainAtk": 1,
      "gainSpAtk": 0,
      "gainDef": 0,
      "gainSpDef": 0,
      "fillA": 0
    },
    {
      "level": 77,
      "expRequired": 1616040,
      "gainHP": 1,
      "gainAtk": 1,
      "gainSpAtk": 0,
      "gainDef": 0,
      "gainSpDef": 0,
      "fillA": 0
    },
    {
      "level": 78,
      "expRequired": 1646040,
      "gainHP": 1,
      "gainAtk": 1,
      "gainSpAtk": 0,
      "gainDef": 0,
      "gainSpDef": 0,
      "fillA": 0
    },
    {
      "level": 79,
      "expRequired": 1676040,
      "gainHP": 1,
      "gainAtk": 1,
      "gainSpAtk": 0,
      "gainDef": 0,
      "gainSpDef": 0,
      "fillA": 0
    },
    {
      "level": 80,
      "expRequired": 1706040,
      "gainHP": 1,
      "gainAtk": 0,
      "gainSpAtk": 1,
      "gainDef": 0,
      "gainSpDef": 0,
      "fillA": 0
    },
    {
      "level": 81,
      "expRequired": 1736040,
      "gainHP": 1,
      "gainAtk": 0,
      "gainSpAtk": 1,
      "gainDef": 0,
      "gainSpDef": 0,
      "fillA": 0
    },
    {
      "level": 82,
      "expRequired": 1766040,
      "gainHP": 1,
      "gainAtk": 0,
      "gainSpAtk": 1,
      "gainDef": 0,
      "gainSpDef": 0,
      "fillA": 0
    },
    {
      "level": 83,
      "expRequired": 1796040,
      "gainHP": 1,
      "gainAtk": 0,
      "gainSpAtk": 1,
      "gainDef": 0,
      "gainSpDef": 0,
      "fillA": 0
    },
    {
      "level": 84,
      "expRequired": 1826040,
      "gainHP": 1,
      "gainAtk": 0,
      "gainSpAtk": 1,
      "gainDef": 0,
      "gainSpDef": 0,
      "fillA": 0
    },
    {
      "level": 85,
      "expRequired": 1856040,
      "gainHP": 1,
      "gainAtk": 0,
      "gainSpAtk": 1,
      "gainDef": 0,
      "gainSpDef": 0,
      "fillA": 0
    },
    {
      "level": 86,
      "expRequired": 1886040,
      "gainHP": 1,
      "gainAtk": 0,
      "gainSpAtk": 1,
      "gainDef": 0,
      "gainSpDef": 0,
      "fillA": 0
    },
    {
      "level": 87,
      "expRequired": 1916040,
      "gainHP": 1,
      "gainAtk": 0,
      "gainSpAtk": 1,
      "gainDef": 0,
      "gainSpDef": 0,
      "fillA": 0
    },
    {
      "level": 88,
      "expRequired": 1946040,
      "gainHP": 1,
      "gainAtk": 0,
      "gainSpAtk": 1,
      "gainDef": 0,
      "gainSpDef": 0,
      "fillA": 0
    },
    {
      "level": 89,
      "expRequired": 1976040,
      "gainHP": 1,
      "gainAtk": 0,
      "gainSpAtk": 1,
      "gainDef": 0,
      "gainSpDef": 0,
      "fillA": 0
    },
    {
      "level": 90,
      "expRequired": 2006040,
      "gainHP": 1,
      "gainAtk": 1,
      "gainSpAtk": 1,
      "gainDef": 0,
      "gainSpDef": 0,
      "fillA": 0
    },
    {
      "level": 91,
      "expRequired": 2036040,
      "gainHP": 1,
      "gainAtk": 1,
      "gainSpAtk": 1,
      "gainDef": 0,
      "gainSpDef": 0,
      "fillA": 0
    },
    {
      "level": 92,
      "expRequired": 2066040,
      "gainHP": 1,
      "gainAtk": 1,
      "gainSpAtk": 1,
      "gainDef": 0,
      "gainSpDef": 0,
      "fillA": 0
    },
    {
      "level": 93,
      "expRequired": 2096040,
      "gainHP": 1,
      "gainAtk": 1,
      "gainSpAtk": 1,
      "gainDef": 0,
      "gainSpDef": 0,
      "fillA": 0
    },
    {
      "level": 94,
      "expRequired": 2126040,
      "gainHP": 1,
      "gainAtk": 1,
      "gainSpAtk": 1,
      "gainDef": 0,
      "gainSpDef": 0,
      "fillA": 0
    },
    {
      "level": 95,
      "expRequired": 2156040,
      "gainHP": 1,
      "gainAtk": 1,
      "gainSpAtk": 1,
      "gainDef": 0,
      "gainSpDef": 0,
      "fillA": 0
    },
    {
      "level": 96,
      "expRequired": 2186040,
      "gainHP": 1,
      "gainAtk": 1,
      "gainSpAtk": 1,
      "gainDef": 0,
      "gainSpDef": 0,
      "fillA": 0
    },
    {
      "level": 97,
      "expRequired": 2216040,
      "gainHP": 1,
      "gainAtk": 1,
      "gainSpAtk": 1,
      "gainDef": 0,
      "gainSpDef": 0,
      "fillA": 0
    },
    {
      "level": 98,
      "expRequired": 2246040,
      "gainHP": 1,
      "gainAtk": 1,
      "gainSpAtk": 1,
      "gainDef": 0,
      "gainSpDef": 0,
      "fillA": 0
    },
    {
      "level": 99,
      "expRequired": 2276040,
      "gainHP": 1,
      "gainAtk": 1,
      "gainSpAtk": 1,
      "gainDef": 0,
      "gainSpDef": 0,
      "fillA": 0
    },
    {
      "level": 100,
      "expRequired": 2306040,
      "gainHP": 1,
      "gainAtk": 1,
      "gainSpAtk": 1,
      "gainDef": 0,
      "gainSpDef": 0,
      "fillA": 0
    }
  ]
}
